dinkleberg/__init__.py
dinkleberg/dependency.py
dinkleberg/dependency_configurator.py
dinkleberg/dependency_scope.py
dinkleberg/descriptor.py
dinkleberg/typing.py
dinkleberg-0.1.0.dist-info/METADATA
dinkleberg-0.1.0.dist-info/WHEEL
dinkleberg-0.1.0.dist-info/RECORD
