Metadata-Version: 2.4
Name: dinkleberg
Version: 0.1.0
Summary: Your friendly neighbour when it comes to dependency management.
Project-URL: Homepage, https://github.com/DavidVollmers/dinkleberg
Project-URL: Documentation, https://github.com/DavidVollmers/dinkleberg/blob/main/libs/dinkleberg/README.md
Project-URL: Repository, https://github.com/DavidVollmers/dinkleberg.git
Project-URL: Issues, https://github.com/DavidVollmers/dinkleberg/issues
Project-URL: Changelog, https://github.com/DavidVollmers/dinkleberg/blob/main/CHANGELOG.md
Keywords: automation,dependency,package-management
Classifier: Development Status :: 3 - Alpha
Classifier: Intended Audience :: Developers
Classifier: License :: OSI Approved :: MIT License
Classifier: Operating System :: OS Independent
Classifier: Programming Language :: Python :: 3
Classifier: Programming Language :: Python :: 3.13
Classifier: Topic :: Software Development :: Libraries :: Python Modules
Requires-Python: >=3.13
